Workbook

Sheet sumif
A1: Party Names | B1: Sales
A2: SwiftNova Enterprises | B2: 24750
A3: BluePeak Solutions | B3: 43891
A4: EliteCrest Innovations | B4: 36623
A5: QuantumByte Technologies | B5: 33686 | E5: Party Names | F5: Total Sales | G5: Average Sale | H5: Count Of Sale
A6: GoldenLeaf Ventures | B6: 37488 | E6: SwiftNova Enterprises | F6: {=SUMIF($A$2:$A$339,E6:E15,B2)} -> 805869 | G6: {=AVERAGEIF($A$2:$A$339,$E$6:$E$15,$B$2:$B$340)} -> 28781.036 | H6: {=COUNTIF($A$2:$A$339,$E$6:$E$15)} -> 28
A7: UrbanNest Interiors | B7: 21012 | E7: BluePeak Solutions | F7: 847774 | G7: 30277.643 | H7: 28
A8: Vertex Synergy | B8: 34133 | E8: EliteCrest Innovations | F8: 896206 | G8: 27157.758 | H8: 33
A9: EverGlow Essentials | B9: 25015 | E9: QuantumByte Technologies | F9: 913593 | G9: 27684.636 | H9: 33
A10: TruHarvest Organics | B10: 24185 | E10: GoldenLeaf Ventures | F10: 1361323 | G10: 32412.452 | H10: 42
A11: StellarEdge Consulting | B11: 27419 | E11: UrbanNest Interiors | F11: 590284 | G11: 31067.579 | H11: 19
A12: SwiftNova Enterprises | B12: 20989 | E12: Vertex Synergy | F12: 1012579 | G12: 29781.735 | H12: 34
A13: BluePeak Solutions | B13: 37327 | E13: EverGlow Essentials | F13: 1176087 | G13: 29402.175 | H13: 40
A14: EliteCrest Innovations | B14: 14753 | E14: TruHarvest Organics | F14: 1408626 | G14: 30622.304 | H14: 46
A15: QuantumByte Technologies | B15: 16689 | E15: StellarEdge Consulting | F15: 1162990 | G15: 33228.286 | H15: 35
A16: GoldenLeaf Ventures | B16: 38507 | E16: Total Sale | F16: =SUM(F6:F15) -> 10175331
A17: EliteCrest Innovations | B17: 14720
A18: QuantumByte Technologies | B18: 38768
A19: GoldenLeaf Ventures | B19: 45280
A20: UrbanNest Interiors | B20: 49176
A21: Vertex Synergy | B21: 39695
A22: EverGlow Essentials | B22: 19380
A23: TruHarvest Organics | B23: 32705
A24: StellarEdge Consulting | B24: 37700
A25: Vertex Synergy | B25: 25793
A26: EverGlow Essentials | B26: 10459
A27: TruHarvest Organics | B27: 31197
A28: StellarEdge Consulting | B28: 28369
... A339: EverGlow Essentials | B339: 17811
B340: =SUM(B2:B339) -> 10175331

Sheet illustration Group

Sheet sparkline group
B2: Names | C2: Hindi | D2: English | E2: Maths | F2: Science | G2: sparkline | H2: column | I2: winloss
B3: Aarav Sharma | C3: 47 | D3: 90 | E3: 75 | F3: 40
B4: Riya Verma | C4: 20 | D4: 2 | E4: 73 | F4: 47
B5: Vivaan Mehta | C5: 22 | D5: 77 | E5: 29 | F5: 93
B6: Ananya Iyer | C6: 58 | D6: 80 | E6: 28 | F6: 92
B7: Karan Patel | C7: 63 | D7: 85 | E7: 78 | F7: 85
B8: Sanya Malhotra | C8: 43 | D8: 20 | E8: 66 | F8: 20
B9: Rahul Nair | C9: 21 | D9: 27 | E9: 40 | F9: 20
B10: Pooja Deshmukh | C10: 21 | D10: 35 | E10: 36 | F10: 41
B11: Aditya Reddy | C11: 61 | D11: 19 | E11: 25 | F11: 73
B12: Meera Kapoor | C12: 69 | D12: 42 | E12: 59 | F12: 41
B13: Rohan Bansal | C13: 27 | D13: 75 | E13: 68 | F13: 79
B14: Ishita Choudhary | C14: 76 | D14: 54 | E14: 41 | F14: 45
... B17: Kabir Saxena | C17: 15 | D17: 95 | E17: 29 | F17: 64

Sheet format
A1: s no | B1: busssiness name | C1: Quantity | D1: Rate | E1: Amount
A2: 1 | B2: ZyroTech Solutions | C2: 159 | D2: 3407 | E2: =C2*D2 -> 541713
A3: 2 | B3: InnoVibe India | C3: 191 | D3: 1935 | E3: =C3*D3 -> 369585
A4: 3 | B4: NextGen Bharat | C4: 163 | D4: 4237 | E4: =C4*D4 -> 690631
A5: 4 | B5: UrbanNova Ventures | C5: 131 | D5: 3214 | E5: =C5*D5 -> 421034
A6: 5 | B6: Apex India Enterprises | C6: 112 | D6: 4381 | E6: =C6*D6 -> 490672
A7: 6 | B7: EliteCore Solutions | C7: 141 | D7: 4479 | E7: =C7*D7 -> 631539
A8: 7 | B8: PrimeEdge Consulting | C8: 179 | D8: 4223 | E8: =C8*D8 -> 755917
A9: 8 | B9: BharatRise Pvt Ltd | C9: 157 | D9: 3076 | E9: =C9*D9 -> 482932
A10: 9 | B10: DesiCraft Industries | C10: 114 | D10: 1447 | E10: =C10*D10 -> 164958
A11: 10 | B11: Udaan Ventures India | C11: 169 | D11: 1714 | E11: =C11*D11 -> 289666

Sheet link
D8: Data creation

Sheet spell check
F5: cow | I5: answer
F6: cow
F7: elephant
F8: elephant
F9: cow

Sheet ifs
A1: Name | B1: Rating | C1: Status
A2: Bharat Innovations | B2: 2 | C2: {=_xlfn.IFS(B2<=3,"Good",B2>3,"excellent")} -> Good
A3: Green Leaf Enterprises | B3: 3 | C3: {=_xlfn.IFS(B3<=3,"Good",B3>3,"excellent")} -> Good
A4: Urban Pulse Technologies | B4: 4 | C4: {=_xlfn.IFS(B4<=3,"Good",B4>3,"excellent")} -> excellent
A5: Mystic India Exports | B5: 5 | C5: {=_xlfn.IFS(B5<=3,"Good",B5>3,"excellent")} -> excellent
A6: Golden Horizon Ventures | B6: 1 | C6: {=_xlfn.IFS(B6<=3,"Good",B6>3,"excellent")} -> Good
A7: Eternal Traditions | B7: 5 | C7: {=_xlfn.IFS(B7<=3,"Good",B7>3,"excellent")} -> excellent
A8: Apex Solutions | B8: 2 | C8: {=_xlfn.IFS(B8<=3,"Good",B8>3,"excellent")} -> Good
A9: Harmony Foods | B9: 2 | C9: {=_xlfn.IFS(B9<=3,"Good",B9>3,"excellent")} -> Good
A10: Pure Essence Skincare | B10: 2 | C10: {=_xlfn.IFS(B10<=3,"Good",B10>3,"excellent")} -> Good
A11: Zenith Construction Co. | B11: 2 | C11: {=_xlfn.IFS(B11<=3,"Good",B11>3,"excellent")} -> Good
A12: Radiant Health Systems | B12: 3 | C12: {=_xlfn.IFS(B12<=3,"Good",B12>3,"excellent")} -> Good
A13: Divine Creations | B13: 2 | C13: {=_xlfn.IFS(B13<=3,"Good",B13>3,"excellent")} -> Good
... A331: Legacy Health Co. | B331: 3 | C331: {=_xlfn.IFS(B331<=3,"Good",B331>3,"excellent")} -> Good

Sheet sumifs
A1: Party Name | B1: January | C1: February | D1: March | E1: April | F1: May | G1: June | H1: July | I1: August | J1: September | K1: October | L1: November | M1: December | N1: Total
A2: Bharat Innovations | B2: {=SUMIFS('Data creation'!$L$3:$L$994,'Data creation'!$C$3:$C$994,sumifs!A2:A325,'Data creation'!$B$3:$B$994,sumifs!B1:N1)} -> 0 | C2: 0 | D2: 0 | E2: 88580 | F2: 0 | G2: 0 | H2: 0 | I2: 0 | J2: 0 | K2: 0 | L2: 0 | M2: 0 | N2: 0
A3: Green Leaf Enterprises | B3: 0 | C3: 0 | D3: 0 | E3: 106405 | F3: 0 | G3: 0 | H3: 0 | I3: 0 | J3: 0 | K3: 0 | L3: 0 | M3: 0 | N3: 0
A4: Urban Pulse Technologies | B4: 0 | C4: 0 | D4: 0 | E4: 71031 | F4: 0 | G4: 0 | H4: 0 | I4: 0 | J4: 0 | K4: 0 | L4: 0 | M4: 0 | N4: 0
A5: Mystic India Exports | B5: 0 | C5: 0 | D5: 0 | E5: 78594 | F5: 0 | G5: 0 | H5: 0 | I5: 0 | J5: 0 | K5: 0 | L5: 0 | M5: 0 | N5: 0
A6: Golden Horizon Ventures | B6: 0 | C6: 0 | D6: 0 | E6: 309415 | F6: 0 | G6: 0 | H6: 0 | I6: 0 | J6: 0 | K6: 0 | L6: 0 | M6: 0 | N6: 0
A7: Eternal Traditions | B7: 0 | C7: 0 | D7: 0 | E7: 297776 | F7: 0 | G7: 0 | H7: 0 | I7: 0 | J7: 0 | K7: 0 | L7: 0 | M7: 0 | N7: 0
A8: Apex Solutions | B8: 0 | C8: 0 | D8: 0 | E8: 172885 | F8: 0 | G8: 0 | H8: 0 | I8: 0 | J8: 0 | K8: 0 | L8: 0 | M8: 0 | N8: 0
A9: Crystal Waters Resort | B9: 0 | C9: 0 | D9: 0 | E9: 0 | F9: 248023 | G9: 0 | H9: 0 | I9: 0 | J9: 0 | K9: 0 | L9: 0 | M9: 0 | N9: 0
A10: Excellence Tutors | B10: 0 | C10: 0 | D10: 0 | E10: 0 | F10: 270958 | G10: 0 | H10: 0 | I10: 0 | J10: 0 | K10: 0 | L10: 0 | M10: 0 | N10: 0
A11: Horizon Builders | B11: 0 | C11: 0 | D11: 0 | E11: 0 | F11: 326271 | G11: 0 | H11: 0 | I11: 0 | J11: 0 | K11: 0 | L11: 0 | M11: 0 | N11: 0
A12: Synergy Tech Solutions | B12: 0 | C12: 0 | D12: 0 | E12: 0 | F12: 203862 | G12: 0 | H12: 0 | I12: 0 | J12: 0 | K12: 0 | L12: 0 | M12: 0 | N12: 0
A13: Classic Heritage Crafts | B13: 0 | C13: 0 | D13: 0 | E13: 0 | F13: 233521 | G13: 0 | H13: 0 | I13: 0 | J13: 0 | K13: 0 | L13: 0 | M13: 0 | N13: 0
A14: Prime Focus Media | B14: 0 | C14: 0 | D14: 0 | E14: 0 | F14: 282476 | G14: 0 | H14: 0 | I14: 0 | J14: 0 | K14: 0 | L14: 0 | M14: 0 | N14: 0
... A325: Legacy Health Co. | B325: 0 | C325: 277842 | D325: 0 | E325: 0 | F325: 0 | G325: 0 | H325: 0 | I325: 0 | J325: 0 | K325: 0 | L325: 0 | M325: 0 | N325: 0

Sheet sumtotal
B2: Name | C2: Category | D2: Product Name | E2: State | F2: Gender | G2: Quantity
B3: Horizon Wellness | C3: Decor | D3: Car accessories | E3: Assam | F3: Female | G3: 19
B4: True Value Electronics | C4: Decor | D4: Car accessories | E4: Punjab | F4: Female | G4: 18
B5: Harmony Homes Realty | C5: Decor | D5: Car accessories | E5: Chhattisgarh | F5: Female | G5: 20
B6: Stellar Advertising | C6: Decor | D6: Car accessories | E6: West Bengal | F6: Female | G6: 17
B7: Modern Trends Retail | C7: Decor | D7: Car accessories | E7: Madhya Pradesh | F7: Male | G7: 14
B8: Global Spectrum Consulting | C8: Decor | D8: Car accessories | E8: Jharkhand | F8: Male | G8: 20
B9: Apex Solutions | C9: Fashion | D9: Women dress | E9: Gujarat | F9: Male | G9: 55
B10: Radiant Vision Studios | C10: Decor | D10: Home décor | E10: Gujarat | F10: Female | G10: 17
B11: Noble Travel Services | C11: Decor | D11: Home décor | E11: Uttar Pradesh | F11: Female | G11: 20
B12: Bright Future Academy | C12: Decor | D12: Home décor | E12: Uttar Pradesh | F12: Female | G12: 13
B13: Visionary Health Systems | C13: Decor | D13: Home décor | E13: Madhya Pradesh | F13: Female | G13: 12
B14: Apex Retailers | C14: Decor | D14: Home décor | E14: Maharashtra | F14: Female | G14: 12
... B17: Classic Trends Fashion | C17: Decor | D17: Home décor | E17: Madhya Pradesh | F17: Male | G17: 20
G18: =SUBTOTAL(9,G3:G17) -> 298

Sheet Sheet1

Sheet lookup formula
A1: Name | B1: Category | C1: Product Name | D1: Region | E1: City | F1: State | G1: Gender
A2: Harmony Foods | B2: {=VLOOKUP(A2,Data!$B$2:$K$331,{2,3,4,5,6,7},FALSE)} -> Fashion | C2: Women dress | D2: West | E2: Pune | F2: Maharashtra | G2: Male
A3: Legacy Innovations | B3: {=VLOOKUP(A3,Data!$B$2:$K$331,{2,3,4,5,6,7},FALSE)} -> Fashion | C3: Suit | D3: South | E3: Chennai | F3: Tamil Nadu | G3: Female
A4: Apex Realty Services | B4: {=VLOOKUP(A4,Data!$B$2:$K$331,{2,3,4,5,6,7},FALSE)} -> Fashion | C4: Suit | D4: Central | E4: Indore | F4: Madhya Pradesh | G4: Male
A5: Apex Travel Ventures | B5: {=VLOOKUP(A5,Data!$B$2:$K$331,{2,3,4,5,6,7},FALSE)} -> Electronic | C5: Laptop | D5: Northeast | E5: Guwahati | F5: Assam | G5: Female
A6: Pure Health Ventures | B6: {=VLOOKUP(A6,Data!$B$2:$K$331,{2,3,4,5,6,7},FALSE)} -> Fashion | C6: Saree | D6: South | E6: Madurai | F6: Tamil Nadu | G6: Female
A7: Radiant Ventures | B7: {=VLOOKUP(A7,Data!$B$2:$K$331,{2,3,4,5,6,7},FALSE)} -> Electronic | C7: Laptop | D7: North | E7: Shimla | F7: Himachal Pradesh | G7: Female
A8: Synergy Tech Solutions | B8: {=VLOOKUP(A8,Data!$B$2:$K$331,{2,3,4,5,6,7},FALSE)} -> Fashion | C8: Saree | D8: East | E8: Patna | F8: Bihar | G8: Male
A9: Visionary Tours | B9: {=VLOOKUP(A9,Data!$B$2:$K$331,{2,3,4,5,6,7},FALSE)} -> Fashion | C9: Suit | D9: North | E9: Dehradun | F9: Uttarakhand | G9: Female
A10: Classic Heritage Crafts | B10: {=VLOOKUP(A10,Data!$B$2:$K$331,{2,3,4,5,6,7},FALSE)} -> Fashion | C10: Saree | D10: West | E10: Vadodara | F10: Gujarat | G10: Male
A37: Name | B37: Category | C37: Product Name | D37: Region | E37: City | F37: State | G37: Gender
A38: Harmony Foods | B38: {=_xlfn.XLOOKUP(A38,Data!$B$2:$B$331,Data!$C$2:$H$331)} -> Fashion | C38: Women dress | D38: West | E38: Pune | F38: Maharashtra | G38: Male
A39: Legacy Innovations | B39: {=_xlfn.XLOOKUP(A39,Data!$B$2:$B$331,Data!$C$2:$H$331)} -> Fashion | C39: Suit | D39: South | E39: Chennai | F39: Tamil Nadu | G39: Female
A40: Apex Realty Services | B40: {=_xlfn.XLOOKUP(A40,Data!$B$2:$B$331,Data!$C$2:$H$331)} -> Fashion | C40: Suit | D40: Central | E40: Indore | F40: Madhya Pradesh | G40: Male
A41: Apex Travel Ventures | B41: {=_xlfn.XLOOKUP(A41,Data!$B$2:$B$331,Data!$C$2:$H$331)} -> Electronic | C41: Laptop | D41: Northeast | E41: Guwahati | F41: Assam | G41: Female
A42: Pure Health Ventures | B42: {=_xlfn.XLOOKUP(A42,Data!$B$2:$B$331,Data!$C$2:$H$331)} -> Fashion | C42: Saree | D42: South | E42: Madurai | F42: Tamil Nadu | G42: Female
A43: Radiant Ventures | B43: {=_xlfn.XLOOKUP(A43,Data!$B$2:$B$331,Data!$C$2:$H$331)} -> Electronic | C43: Laptop | D43: North | E43: Shimla | F43: Himachal Pradesh | G43: Female
A44: Synergy Tech Solutions | B44: {=_xlfn.XLOOKUP(A44,Data!$B$2:$B$331,Data!$C$2:$H$331)} -> Fashion | C44: Saree | D44: East | E44: Patna | F44: Bihar | G44: Male
A45: Visionary Tours | B45: {=_xlfn.XLOOKUP(A45,Data!$B$2:$B$331,Data!$C$2:$H$331)} -> Fashion | C45: Suit | D45: North | E45: Dehradun | F45: Uttarakhand | G45: Female
A46: Classic Heritage Crafts | B46: {=_xlfn.XLOOKUP(A46,Data!$B$2:$B$331,Data!$C$2:$H$331)} -> Fashion | C46: Saree | D46: West | E46: Vadodara | F46: Gujarat | G46: Male

Sheet Data creation
A2: date | B2: Month | C2: Name | D2: Category | E2: Product Name | F2: State | G2: Gender | H2: Quantity | I2: Cost | J2: Price | K2: Purchase Cost | L2: Sale Price | M2: Profit | N2: Status
A3: 45454 | B3: june | C3: Horizon Wellness | D3: Decor | E3: Car accessories | F3: Assam | G3: Female | H3: 17 | I3: 938 | J3: 938 | K3: =H3*I3 -> 15946 | L3: =H3*J3 -> 15946 | M3: =L3-K3 -> 0 | N3: =IF(M3>0,"profit","loss") -> loss
A4: 45455 | B4: june | C4: True Value Electronics | D4: Decor | E4: Car accessories | F4: Punjab | G4: Female | H4: 18 | I4: 920 | J4: 1360 | K4: =H4*I4 -> 16560 | L4: =H4*J4 -> 24480 | M4: =L4-K4 -> 7920 | N4: =IF(M4>0,"profit","loss") -> profit
A5: 45456 | B5: june | C5: Harmony Homes Realty | D5: Decor | E5: Car accessories | F5: Chhattisgarh | G5: Female | H5: 20 | I5: 731 | J5: 1186 | K5: =H5*I5 -> 14620 | L5: =H5*J5 -> 23720 | M5: =L5-K5 -> 9100 | N5: =IF(M5>0,"profit","loss") -> profit
A6: 45457 | B6: june | C6: Stellar Advertising | D6: Decor | E6: Car accessories | F6: West Bengal | G6: Female | H6: 17 | I6: 750 | J6: 793 | K6: =H6*I6 -> 12750 | L6: =H6*J6 -> 13481 | M6: =L6-K6 -> 731 | N6: =IF(M6>0,"profit","loss") -> profit
A7: 45459 | B7: june | C7: Modern Trends Retail | D7: Decor | E7: Car accessories | F7: Madhya Pradesh | G7: Male | H7: 14 | I7: 906 | J7: 1327 | K7: =H7*I7 -> 12684 | L7: =H7*J7 -> 18578 | M7: =L7-K7 -> 5894 | N7: =IF(M7>0,"profit","loss") -> profit
A8: 45460 | B8: june | C8: Global Spectrum Consulting | D8: Decor | E8: Car accessories | F8: Jharkhand | G8: Male | H8: 20 | I8: 699 | J8: 1400 | K8: =H8*I8 -> 13980 | L8: =H8*J8 -> 28000 | M8: =L8-K8 -> 14020 | N8: =IF(M8>0,"profit","loss") -> profit
A9: 45389 | B9: april | C9: Apex Solutions | D9: Fashion | E9: Women dress | F9: Gujarat | G9: Male | H9: 55 | I9: 637 | J9: 1143 | K9: =H9*I9 -> 35035 | L9: =H9*J9 -> 62865 | M9: =L9-K9 -> 27830 | N9: =IF(M9>0,"profit","loss") -> profit
A10: 45472 | B10: june | C10: Radiant Vision Studios | D10: Decor | E10: Home décor | F10: Gujarat | G10: Female | H10: 17 | I10: 537 | J10: 1350 | K10: =H10*I10 -> 9129 | L10: =H10*J10 -> 22950 | M10: =L10-K10 -> 13821 | N10: =IF(M10>0,"profit","loss") -> profit
A11: 45473 | B11: june | C11: Noble Travel Services | D11: Decor | E11: Home décor | F11: Uttar Pradesh | G11: Female | H11: 20 | I11: 875 | J11: 911 | K11: =H11*I11 -> 17500 | L11: =H11*J11 -> 18220 | M11: =L11-K11 -> 720 | N11: =IF(M11>0,"profit","loss") -> profit
A12: 45474 | B12: july | C12: Bright Future Academy | D12: Decor | E12: Home décor | F12: Uttar Pradesh | G12: Female | H12: 13 | I12: 917 | J12: 1315 | K12: =H12*I12 -> 11921 | L12: =H12*J12 -> 17095 | M12: =L12-K12 -> 5174 | N12: =IF(M12>0,"profit","loss") -> profit
A13: 45476 | B13: july | C13: Visionary Health Systems | D13: Decor | E13: Home décor | F13: Madhya Pradesh | G13: Female | H13: 12 | I13: 980 | J13: 1462 | K13: =H13*I13 -> 11760 | L13: =H13*J13 -> 17544 | M13: =L13-K13 -> 5784 | N13: =IF(M13>0,"profit","loss") -> profit
A14: 45477 | B14: july | C14: Apex Retailers | D14: Decor | E14: Home décor | F14: Maharashtra | G14: Female | H14: 12 | I14: 734 | J14: 1181 | K14: =H14*I14 -> 8808 | L14: =H14*J14 -> 14172 | M14: =L14-K14 -> 5364 | N14: =IF(M14>0,"profit","loss") -> profit
... A994: 45712 | B994: february | C994: Legacy Health Co. | D994: Fashion | E994: Suit | F994: Punjab | G994: Male | H994: 84 | I994: 738 | J994: 1080 | K994: =H994*I994 -> 61992 | L994: =H994*J994 -> 90720 | M994: =L994-K994 -> 28728 | N994: =IF(M994>0,"profit","loss") -> profit

Sheet filter
C6: Create Search Box using filter Formula
C8: Visionary Tours
C18: Name | D18: Category | E18: Product Name | F18: State | G18: Gender
C19: {=_xlfn._xlws.FILTER('Data creation'!A3:N994,'Data creation'!C3:C994=filter!C8)} -> 45453 | D19: june | E19: Visionary Tours | F19: Fashion | G19: Suit | H19: Uttarakhand | I19: Female | J19: 68 | K19: 651 | L19: 1061 | M19: 44268 | N19: 72148 | O19: 27880 | P19: profit
C20: 45453 | D20: june | E20: Visionary Tours | F20: Fashion | G20: Suit | H20: Uttarakhand | I20: Female | J20: 90 | K20: 862 | L20: 902 | M20: 77580 | N20: 81180 | O20: 3600 | P20: profit
C21: 45453 | D21: june | E21: Visionary Tours | F21: Fashion | G21: Suit | H21: Uttarakhand | I21: Female | J21: 72 | K21: 804 | L21: 833 | M21: 57888 | N21: 59976 | O21: 2088 | P21: profit

Sheet Data
A1: S no | B1: Name | C1: Category | D1: Product Name | E1: Region | F1: City | G1: State | H1: Gender | I1: Quantity | J1: Rate | K1: Amount
A2: 1 | B2: Bharat Innovations | C2: Electronic | D2: Speaker | E2: North | F2: Delhi | G2: Delhi | H2: Male | I2: 4292 | J2: 783 | K2: 3360636
A3: 2 | B3: Green Leaf Enterprises | C3: Electronic | D3: Earbuds | E3: West | F3: Mumbai | G3: Maharashtra | H3: Male | I3: 8037 | J3: 578 | K3: 4645386
A4: 3 | B4: Urban Pulse Technologies | C4: Electronic | D4: Earbuds | E4: East | F4: Kolkata | G4: West Bengal | H4: Male | I4: 2415 | J4: 631 | K4: 1523865
A5: 4 | B5: Mystic India Exports | C5: Electronic | D5: Earbuds | E5: South | F5: Chennai | G5: Tamil Nadu | H5: Male | I5: 3941 | J5: 905 | K5: 3566605
A6: 5 | B6: Golden Horizon Ventures | C6: Fashion | D6: Women dress | E6: South | F6: Bengaluru | G6: Karnataka | H6: Male | I6: 4607 | J6: 813 | K6: 3745491
A7: 6 | B7: Eternal Traditions | C7: Fashion | D7: Women dress | E7: South | F7: Hyderabad | G7: Telangana | H7: Male | I7: 4261 | J7: 954 | K7: 4064994
A8: 7 | B8: Apex Solutions | C8: Fashion | D8: Women dress | E8: West | F8: Ahmedabad | G8: Gujarat | H8: Male | I8: 9084 | J8: 610 | K8: 5541240
A9: 8 | B9: Harmony Foods | C9: Fashion | D9: Women dress | E9: West | F9: Pune | G9: Maharashtra | H9: Male | I9: 6694 | J9: 742 | K9: 4966948
A10: 9 | B10: Pure Essence Skincare | C10: Electronic | D10: Speaker | E10: North | F10: Jaipur | G10: Rajasthan | H10: Female | I10: 2678 | J10: 567 | K10: 1518426
A11: 10 | B11: Zenith Construction Co. | C11: Electronic | D11: Speaker | E11: West | F11: Surat | G11: Gujarat | H11: Female | I11: 1631 | J11: 508 | K11: 828548
A12: 11 | B12: Radiant Health Systems | C12: Electronic | D12: Speaker | E12: North | F12: Lucknow | G12: Uttar Pradesh | H12: Female | I12: 4171 | J12: 643 | K12: 2681953
A13: 12 | B13: Divine Creations | C13: Electronic | D13: Speaker | E13: North | F13: Kanpur | G13: Uttar Pradesh | H13: Female | I13: 4283 | J13: 804 | K13: 3443532
... A331: 330 | B331: Legacy Health Co. | C331: Fashion | D331: Suit | E331: North | F331: Amritsar | G331: Punjab | H331: Male | I331: 5246 | J331: 653 | K331: 3425638
K332: =SUBTOTAL(9,K2:K331) -> 1386308853

Sheet Dget
A1: Name | B1: Quantity | C1: Quantity
A2: Harmony Foods | B2: Maharastra | C2: =DGET(Data!A1:K331,Dget!C1,Dget!A1:A2) -> 6694

Sheet Dsum
C3: Name | D3: Month
C4: Harmony Foods | D4: febraury
C14: Dsum
C16: =DSUM(Data!A1:K331,Data!K1,Dsum!C3:D4) -> 0

Sheet large+small
N3: Party Names | O3: Sales
N4: Harmony Foods | O4: 993659
N5: Pure Essence Skincare | O5: 564252
N6: Zenith Construction Co. | O6: 898645 | S6: Rank | T6: Number
N7: Radiant Health Systems | O7: 783469 | S7: 1 | T7: {=LARGE(O4:O23,S7:S11)} -> 995011
N8: Divine Creations | O8: 821743 | S8: 2 | T8: 993659
N9: Metro Tech Solutions | O9: 568913 | S9: 3 | T9: 950637
N10: True Path Logistics | O10: 609456 | S10: 4 | T10: 918994
N11: Sacred Roots Apparel | O11: 608609 | S11: 5 | T11: 898645
N12: Quantum Finance Services | O12: 950637
N13: Brilliant Minds Academy | O13: 995011
N14: Visionary Holdings | O14: 746424
N15: Stellar Design Studio | O15: 508792
N16: Classic Cuisines | O16: 576924 | S16: Rank | T16: Number
N17: Bold Ventures | O17: 674474 | S17: 1 | T17: {=SMALL(O4:O23,S17:S21)} -> 508792
N18: Prestige Automobiles | O18: 743014 | S18: 2 | T18: 564252
N19: Elite Marketing Solutions | O19: 720461 | S19: 3 | T19: 568913
N20: Natural Bliss Beverages | O20: 797708 | S20: 4 | T20: 576924
N21: Crystal Clear Solutions | O21: 918994 | S21: 5 | T21: 608609
N22: Modern Trends Fashion | O22: 802656
N23: Heritage Crafts | O23: 898245

Sheet finance
B4: Loan Amount | C4: Annual Interest Rate | D4: Monthly Interest Rate | E4: Loan Term (Years) | F4: Periods (Months)
B5: 100000 | C5: 0.1 | D5: 0.0083333 | E5: 5 | F5: 60
B9: Installment | C9: =PMT(D5,F5,B5) -> -2124.7025
B11: Principle Amount | C11: =PPMT(D5,1,F5,B5) -> -1291.3725
B13: Interest Amount | C13: =IPMT(D5,1,F5,B5) -> -833.33
